project_version_finder/__init__.py
project_version_finder/__main__.py
project_version_finder/cli.py
project_version_finder/finder.py
project_version_finder/py.typed
project_version_finder-0.3.0.dist-info/METADATA
project_version_finder-0.3.0.dist-info/WHEEL
project_version_finder-0.3.0.dist-info/entry_points.txt
project_version_finder-0.3.0.dist-info/RECORD
