Metadata-Version: 2.4
Name: project-version-finder
Version: 0.3.0
Summary: Find __version__ for __init__.py
Project-URL: repository, https://codeberg.org/Pusher2531/project-version-finder.git
Project-URL: issues, https://codeberg.org/Pusher2531/project-version-finder/issues
Author-email: Doug Sojourner <doug@sojournings.org>
License: GNU General Public License v3 (GPLv3)
Keywords: development,finder,installed,manager,typed,version
Classifier: Development Status :: 4 - Beta
Classifier: Intended Audience :: Developers
Classifier: License :: OSI Approved :: GNU General Public License v3 (GPLv3)
Classifier: Natural Language :: English
Classifier: Operating System :: OS Independent
Classifier: Programming Language :: Python :: 3
Classifier: Programming Language :: Python :: 3 :: Only
Classifier: Programming Language :: Python :: 3.6
Classifier: Programming Language :: Python :: 3.7
Classifier: Programming Language :: Python :: 3.8
Classifier: Programming Language :: Python :: 3.9
Classifier: Programming Language :: Python :: 3.10
Classifier: Programming Language :: Python :: 3.11
Classifier: Programming Language :: Python :: 3.12
Classifier: Programming Language :: Python :: 3.13
Classifier: Topic :: Software Development
Classifier: Topic :: Software Development :: Libraries
Classifier: Topic :: Software Development :: Libraries :: Python Modules
Classifier: Typing :: Typed
Requires-Python: <4.0,>=3.6
Requires-Dist: importlib-metadata; python_version < '3.11'
Requires-Dist: importlib; python_version >= '3.11'
Requires-Dist: pathlib
Requires-Dist: tomlkit
